[
    {
      "id": 1,
      "imageUrl": "https://ariel0508.github.io/FlavorTrail/assets/home-4-54446fc6.jpg",
      "content": "超級喜歡這個平台!在這裡我不僅能找到新鮮的食物,還能遇到很多友好的分享者。每次與其他 Buddy 的互動都充滿了正能量,這讓我覺得自己真的成為了這個社群的一部分，謝謝你們！",
      "createdData": "2024-12-10",
      "userId": 2,
      "status": "active"
    },
    {
      "id": 2,
      "imageUrl": "https://images.unsplash.com/photo-1623689048105-a17b1e1936b8?w=900&auto=format&fit=crop&q=60&ixlib=rb-4.0.3&ixid=M3wxMjA3fDB8MHxzZWFyY2h8NHx8Y2hpbmVzZSUyMGZvb2R8ZW58MHx8MHx8fDA%3D",
      "content": "謝謝 Flavor Trail 的大家，今天收到一位超棒的分享者提供的美味午餐！真的很感謝你們的慷慨,讓我在窘困時期不再擔心吃飯問題。這種分享讓我感到社群的溫暖，謝謝你們！",
      "createdData": "2024-11-09",
      "userId": 4,
      "status": "active"
    },
    {
      "id": 3,
      "imageUrl": "https://images.unsplash.com/photo-1585032226651-759b368d7246?w=900&auto=format&fit=crop&q=60&ixlib=rb-4.0.3&ixid=M3wxMjA3fDB8MHxzZWFyY2h8OHx8Y2hpbmVzZSUyMGZvb2R8ZW58MHx8MHx8fDA%3D",
      "content": "成為 Flavor buddy 真的是一件非常有趣的事!我每次分享食物的時候都會特別注意衛生,因為知道它們可能會送到需要的人手中。這不僅是對食物的尊重,也是對這個社群的愛。",
      "createdData": "2024-12-22",
      "userId": 6,
      "status": "active"
    },
    {
      "id": 4,
      "imageUrl": "https://images.unsplash.com/photo-1565958011703-44f9829ba187?w=900&auto=format&fit=crop&q=60&ixlib=rb-4.0.3&ixid=M3wxMjA3fDB8MHxzZWFyY2h8MTR8fGZvb2R8ZW58MHx8MHx8fDA%3D",
      "content": "這個平台不僅提供美味的食物，更提供了一個讓人與人之間充滿關懷的地方，真心感謝！",
      "createdData": "2024-12-02",
      "userId": 8,
      "status": "active"
    },
    {
      "id": 5,
      "imageUrl": "https://images.unsplash.com/photo-1529042410759-befb1204b468?w=900&auto=format&fit=crop&q=60&ixlib=rb-4.0.3&ixid=M3wxMjA3fDB8MHxzZWFyY2h8Mjh8fGZvb2R8ZW58MHx8MHx8fDA%3D",
      "content": "成為 Flavor buddy 真的是一件非常有趣的事!我每次分享食物的時候都會特別注意衛生,因為知道它們可能會送到需要的人手中。這不僅是對食物的尊重,也是對這個社群的愛。",
      "createdData": "2024-12-14",
      "userId": 10,
      "status": "active"
    },
    {
      "id": 6,
      "imageUrl": "https://images.unsplash.com/photo-1565299507177-b0ac66763828?w=900&auto=format&fit=crop&q=60&ixlib=rb-4.0.3&ixid=M3wxMjA3fDB8MHxzZWFyY2h8NDR8fGZvb2R8ZW58MHx8MHx8fDA%3D",
      "content": "成為 Flavor buddy 真的是一件非常有趣的事!我每次分享食物的時候都會特別注意衛生,因為知道它們可能會送到需要的人手中。這不僅是對食物的尊重,也是對這個社群的愛。",
      "createdData": "2024-12-02",
      "userId": 15,
      "status": "archived"
    },
    {
      "id": 7,
      "imageUrl": "https://images.unsplash.com/photo-1541795795328-f073b763494e?w=900&auto=format&fit=crop&q=60&ixlib=rb-4.0.3&ixid=M3wxMjA3fDB8MHxzZWFyY2h8NTJ8fGZvb2R8ZW58MHx8MHx8fDA%3D",
      "content": "很開心可以成為 Flavor buddy，每次的分享活動讓我更深刻體會到付出的快樂，也希望能幫助到更多需要的人！",
      "createdData": "2024-12-04",
      "userId": 13,
      "status": "active"
    },
    {
      "id": 8,
      "imageUrl": "https://images.unsplash.com/photo-1534971525317-ed179568e7f1?w=900&auto=format&fit=crop&q=60&ixlib=rb-4.0.3&ixid=M3wxMjA3fDB8MHxzZWFyY2h8MzR8fGNoaW5lc2UlMjBmb29kfGVufDB8fDB8fHww",
      "content": "感謝 Flavor Trail 提供的機會，今天收到了一份溫暖又美味的午餐，真的是感激不盡！希望更多人能加入這個美好的行動。",
      "createdData": "2024-11-28",
      "userId": 1,
      "status": "archived"
    },
    {
      "id": 9,
      "imageUrl": "https://images.unsplash.com/photo-1604908176997-125f25cc6f3d?w=900&auto=format&fit=crop&q=60&ixlib=rb-4.0.3&ixid=M3wxMjA3fDB8MHxzZWFyY2h8NDB8fGNoaW5lc2UlMjBmb29kfGVufDB8fDB8fHww",
      "content": "每次參與這個平台的活動，都會讓我感受到人與人之間的關懷與溫暖，這是一個充滿正能量的地方！",
      "createdData": "2024-12-17",
      "userId": 19,
      "status": "archived"
    }
  ]